telegram_manager/__init__.py
telegram_manager/config.py
telegram_manager/controller.py
telegram_manager/main.py
telegrammanager-1.0.33.dist-info/METADATA
telegrammanager-1.0.33.dist-info/WHEEL
telegrammanager-1.0.33.dist-info/entry_points.txt
telegrammanager-1.0.33.dist-info/top_level.txt
telegrammanager-1.0.33.dist-info/RECORD
