Metadata-Version: 2.4
Name: TelegramManager
Version: 1.0.33
Summary: Simple Interface for Telegram read and listen
Author-email: Christian Pojoni <christian.pojoni@gmail.com>
License-Expression: MIT
Classifier: Programming Language :: Python :: 3
Classifier: Operating System :: OS Independent
Requires-Python: >=3.7
Requires-Dist: telethon>=1.40.0
Requires-Dist: python-dotenv>=1.1.0
Requires-Dist: click>=8.2.1
Provides-Extra: dev
Requires-Dist: pytest; extra == "dev"
